odoo8_addon_account_bank_statement_import-8.0.1.2.0-py3.8-nspkg.pth
odoo_addons/account_bank_statement_import/README.rst
odoo_addons/account_bank_statement_import/__init__.py
odoo_addons/account_bank_statement_import/__openerp__.py
odoo_addons/account_bank_statement_import/parserlib.py
odoo_addons/account_bank_statement_import/demo/fiscalyear_period.xml
odoo_addons/account_bank_statement_import/demo/partner_bank.xml
odoo_addons/account_bank_statement_import/i18n/account_bank_statement_import.pot
odoo_addons/account_bank_statement_import/i18n/de.po
odoo_addons/account_bank_statement_import/i18n/es.po
odoo_addons/account_bank_statement_import/i18n/fi.po
odoo_addons/account_bank_statement_import/i18n/fr.po
odoo_addons/account_bank_statement_import/i18n/it.po
odoo_addons/account_bank_statement_import/i18n/lt_LT.po
odoo_addons/account_bank_statement_import/i18n/nl.po
odoo_addons/account_bank_statement_import/i18n/pt_BR.po
odoo_addons/account_bank_statement_import/i18n/pt_PT.po
odoo_addons/account_bank_statement_import/i18n/sl.po
odoo_addons/account_bank_statement_import/migrations/8.0.1.0/post-migrate.py
odoo_addons/account_bank_statement_import/models/__init__.py
odoo_addons/account_bank_statement_import/models/account_bank_statement.py
odoo_addons/account_bank_statement_import/models/account_bank_statement_import.py
odoo_addons/account_bank_statement_import/models/account_config_settings.py
odoo_addons/account_bank_statement_import/models/account_journal.py
odoo_addons/account_bank_statement_import/models/res_partner_bank.py
odoo_addons/account_bank_statement_import/static/description/icon.png
odoo_addons/account_bank_statement_import/static/description/icon_src.svg
odoo_addons/account_bank_statement_import/tests/__init__.py
odoo_addons/account_bank_statement_import/tests/test_import_bank_statement.py
odoo_addons/account_bank_statement_import/tests/test_import_file.py
odoo_addons/account_bank_statement_import/tests/test_res_partner_bank.py
odoo8_addon_account_bank_statement_import-8.0.1.2.0.dist-info/METADATA
odoo8_addon_account_bank_statement_import-8.0.1.2.0.dist-info/WHEEL
odoo8_addon_account_bank_statement_import-8.0.1.2.0.dist-info/namespace_packages.txt
odoo8_addon_account_bank_statement_import-8.0.1.2.0.dist-info/top_level.txt
odoo8_addon_account_bank_statement_import-8.0.1.2.0.dist-info/RECORD
